Metadata-Version: 1.0
Name: oaas
Version: 1.6.0
Summary: Operation as a Service
Home-page: UNKNOWN
Author: Bogdan Mustiata
Author-email: bogdan.mustiata@gmail.com
License: BSD
Platform: UNKNOWN
